_updateversion.py
spectrally/__init__.py
spectrally/_class00_SpectralLines.py
spectrally/_class00_check_ion.py
spectrally/_class00_check_ions_table.csv
spectrally/_class00_check_lines.py
spectrally/_class00_compute.py
spectrally/_class00_lines_labels.py
spectrally/_class00_plot.py
spectrally/_class00_plot_spectral_data.py
spectrally/_class01_SpectralModel.py
spectrally/_class01_check_constraints.py
spectrally/_class01_check_model.py
spectrally/_class01_display_models.py
spectrally/_class01_dparams.py
spectrally/_class01_fit_func.py
spectrally/_class01_fit_func_1d.py
spectrally/_class01_interpolate.py
spectrally/_class01_model_dict.py
spectrally/_class01_moments.py
spectrally/_class01_plot.py
spectrally/_class01_show.py
spectrally/_class01_valid.py
spectrally/_class02_SpectralFit.py
spectrally/_class02_binning.py
spectrally/_class02_check_fit.py
spectrally/_class02_compute_fit.py
spectrally/_class02_compute_fit_1d.py
spectrally/_class02_plot_fit.py
spectrally/_class02_plot_valid.py
spectrally/_class02_show.py
spectrally/_class02_x0_scale_bounds.py
spectrally/_saveload.py
spectrally/version.py
spectrally/entrypoints/__init__.py
spectrally/entrypoints/_def.py
spectrally/nist/__init__.py
spectrally/nist/_requests.py
spectrally/openadas/__init__.py
spectrally/openadas/_read_files.py
spectrally/openadas/_requests.py
spectrally/scripts/__init__.py
spectrally/scripts/_dparser.py
spectrally/scripts/spectrally_bash.py
spectrally/scripts/spectrallycustom.py
spectrally/scripts/spectrallyversion.py
spectrally/tests/__init__.py
spectrally/tests/_hxr_pulses.py
spectrally/tests/_setup_teardown.py
spectrally/tests/_spectralfit_input.py
spectrally/tests/test_00_openadas.py
spectrally/tests/test_01_nist.py
spectrally/tests/test_02_SpectralLines.py
spectrally/tests/test_03_SpectralModel.py
spectrally/tests/test_04_SpectralFit.py
spectrally/tests/input/EBIT_spectrally_test.npz
spectrally/tests/input/HXR_pulses.npz
spectrally/tests/input/W_Escan_8.97-keV.hist
spectrally-0.0.7.dist-info/LICENSE
spectrally-0.0.7.dist-info/METADATA
spectrally-0.0.7.dist-info/WHEEL
spectrally-0.0.7.dist-info/entry_points.txt
spectrally-0.0.7.dist-info/top_level.txt
spectrally-0.0.7.dist-info/RECORD
